COPYING
MANIFEST.in
README.html
README.md
README.rst
gsdparser
profisniff
pyprofibus-linuxcnc-hal
setup.py
debian/changelog
debian/compat
debian/control
debian/copyright
debian/gsdparser.install
debian/gsdparser.manpages
debian/profisniff.install
debian/profisniff.manpages
debian/python3-pyprofibus.install
debian/rules
debian/source/format
doc/baudrates.ods
doc/hardware.html
doc/hardware.md
doc/hardware.rst
doc/hardware_fpga.html
doc/hardware_fpga.md
doc/hardware_fpga.rst
doc/pb_frame_format.dia
doc/pb_frame_format.png
doc/pb_telegram_format.dia
doc/pb_telegram_format.png
doc/man/gsdparser.1
doc/man/profisniff.1
doc/man/pyprofibus-linuxcnc-hal.1
doc/ttlserial_to_rs485/ttlserial_to_rs485-cache.lib
doc/ttlserial_to_rs485/ttlserial_to_rs485.kicad_pcb
doc/ttlserial_to_rs485/ttlserial_to_rs485.pdf
doc/ttlserial_to_rs485/ttlserial_to_rs485.pro
doc/ttlserial_to_rs485/ttlserial_to_rs485.sch
examples/example_dummy_inputonly.conf
examples/example_dummy_inputonly.py
examples/example_dummy_oneslave.conf
examples/example_dummy_oneslave.py
examples/example_dummy_twoslaves.conf
examples/example_dummy_twoslaves.py
examples/example_et200s.conf
examples/example_et200s.py
examples/example_s7_315_2dp.conf
examples/example_s7_315_2dp.py
examples/linuxcnc/dummy_phy/dummy.gsd
examples/linuxcnc/dummy_phy/linuxcnc-demo.hal
examples/linuxcnc/dummy_phy/linuxcnc-demo.ini
examples/linuxcnc/dummy_phy/linuxcnc-demo.ngc
examples/linuxcnc/dummy_phy/profibus.hal
examples/linuxcnc/dummy_phy/pyprofibus.conf
examples/linuxcnc/dummy_phy/run-linuxcnc-demo.sh
examples/linuxcnc/et200s/linuxcnc-demo.hal
examples/linuxcnc/et200s/linuxcnc-demo.ini
examples/linuxcnc/et200s/linuxcnc-demo.ngc
examples/linuxcnc/et200s/profibus.hal
examples/linuxcnc/et200s/pyprofibus.conf
examples/linuxcnc/et200s/run-linuxcnc-demo.sh
micropython/Makefile
micropython/README.html
micropython/README.md
micropython/README.rst
micropython/boot.py
micropython/install.sh
micropython/main.py
misc/dummy_compact.gsd
misc/dummy_modular.gsd
pyprofibus.egg-info/PKG-INFO
pyprofibus.egg-info/SOURCES.txt
pyprofibus.egg-info/dependency_links.txt
pyprofibus.egg-info/top_level.txt
